{

"images": [
    "./sprites/card7/card7-0.png",
    "./sprites/card7/card7-1.png",
    "./sprites/card7/card7-2.png",
    "./sprites/card7/card7-3.png",
    "./sprites/card7/card7-4.png",
    "./sprites/card7/card7-5.png",
    "./sprites/card7/card7-6.png",
    "./sprites/card7/card7-7.png",
    "./sprites/card7/card7-8.png",
    "./sprites/card7/card7-9.png"
],

"framerate": 20,
"frames": [
    [0, 0, 1440, 480, 0, 0, 0],
    [0, 480, 1440, 480, 0, 0, 0],
    [0, 960, 1440, 480, 0, 0, 0],
    [0, 1440, 1440, 480, 0, 0, 0],
    [0, 0, 1440, 480, 1, 0, 0],
    [0, 480, 1440, 480, 1, 0, 0],
    [0, 960, 1440, 480, 1, 0, 0],
    [0, 1440, 1440, 480, 1, 0, 0],
    [0, 0, 1440, 480, 2, 0, 0],
    [0, 480, 1440, 480, 2, 0, 0],
    [0, 960, 1440, 480, 2, 0, 0],
    [0, 1440, 1440, 480, 2, 0, 0],
    [0, 0, 1440, 480, 3, 0, 0],
    [0, 480, 1440, 480, 3, 0, 0],
    [0, 960, 1440, 480, 3, 0, 0],
    [0, 1440, 1440, 480, 3, 0, 0],
    [0, 0, 1440, 480, 4, 0, 0],
    [0, 480, 1440, 480, 4, 0, 0],
    [0, 960, 1440, 480, 4, 0, 0],
    [0, 1440, 1440, 480, 4, 0, 0],
    [0, 0, 1440, 480, 5, 0, 0],
    [0, 480, 1440, 480, 5, 0, 0],
    [0, 960, 1440, 480, 5, 0, 0],
    [0, 1440, 1440, 480, 5, 0, 0],
    [0, 0, 1440, 480, 6, 0, 0],
    [0, 480, 1440, 480, 6, 0, 0],
    [0, 960, 1440, 480, 6, 0, 0],
    [0, 1440, 1440, 480, 6, 0, 0],
    [0, 0, 1440, 480, 7, 0, 0],
    [0, 480, 1440, 480, 7, 0, 0],
    [0, 960, 1440, 480, 7, 0, 0],
    [0, 1440, 1440, 480, 7, 0, 0],
    [0, 0, 1440, 480, 8, 0, 0],
    [0, 480, 1440, 480, 8, 0, 0],
    [0, 960, 1440, 480, 8, 0, 0],
    [0, 1440, 1440, 480, 8, 0, 0],
    [0, 0, 1440, 480, 9, 0, 0]
],

"animations": {
    "Strip700": { "frames": [0] },
    "Strip701": { "frames": [1] },
    "Strip702": { "frames": [2] },
    "Strip703": { "frames": [3] },
    "Strip704": { "frames": [4] },
    "Strip705": { "frames": [5] },
    "Strip706": { "frames": [6] },
    "Strip707": { "frames": [7] },
    "Strip708": { "frames": [8] },
    "Strip709": { "frames": [9] },
    "Strip710": { "frames": [10] },
    "Strip711": { "frames": [11] },
    "Strip712": { "frames": [12] },
    "Strip713": { "frames": [13] },
    "Strip714": { "frames": [14] },
    "Strip715": { "frames": [15] },
    "Strip716": { "frames": [16] },
    "Strip717": { "frames": [17] },
    "Strip718": { "frames": [18] },
    "Strip719": { "frames": [19] },
    "Strip720": { "frames": [20] },
    "Strip721": { "frames": [21] },
    "Strip722": { "frames": [22] },
    "Strip723": { "frames": [23] },
    "Strip724": { "frames": [24] },
    "Strip725": { "frames": [25] },
    "Strip726": { "frames": [26] },
    "Strip727": { "frames": [27] },
    "Strip728": { "frames": [28] },
    "Strip729": { "frames": [29] },
    "Strip730": { "frames": [30] },
    "Strip731": { "frames": [31] },
    "Strip732": { "frames": [32] },
    "Strip733": { "frames": [33] },
    "Strip734": { "frames": [34] },
    "Strip735": { "frames": [35] },
    "Strip736": { "frames": [36] }
},

"texturepacker": [
        "SmartUpdateHash: $TexturePacker:SmartUpdate:f17107fcb958647f9d6001b41d9cc152:2c12bb7ea90cb97d003b1fe315aa304d:f8fadb9b21387d522c624c6f1f096d44$",
        "Created with TexturePacker (https://www.codeandweb.com/texturepacker) for EaselJS"
]

}
